ApolloItemsCRUD/__init__.py
ApolloItemsCRUD/apolloInterface.py
ApolloItemsCRUD/apolloService.py
ApolloItemsCRUD/demo.py
ApolloInterface-0.0.2.dist-info/LICENSE
ApolloInterface-0.0.2.dist-info/METADATA
ApolloInterface-0.0.2.dist-info/WHEEL
ApolloInterface-0.0.2.dist-info/top_level.txt
ApolloInterface-0.0.2.dist-info/RECORD
