Metadata-Version: 2.1
Name: ApolloInterface
Version: 0.0.2
Summary: 实现apollo命名空间下items字段的增删改查及版本回溯的接口文件
Home-page: https://github.com/hts559734/ApolloInterface
Author: XvXiao
Author-email: 2081981735@qq.com
Classifier: Programming Language :: Python :: 3
Classifier: License :: OSI Approved :: MIT License
Classifier: Operating System :: OS Independent
License-File: LICENSE
